cerberror/__init__.py
cerberror/errors.py
cerberror/paths.py
cerberror/trans.py
cerberror-0.1.0.dist-info/LICENSE
cerberror-0.1.0.dist-info/METADATA
cerberror-0.1.0.dist-info/WHEEL
cerberror-0.1.0.dist-info/top_level.txt
cerberror-0.1.0.dist-info/RECORD
