Metadata-Version: 2.1
Name: cerberror
Version: 0.1.0
Summary: A package allowing to define own error messages for Cerberus
Home-page: https://github.com/pbrus/cerberror
Author: Przemysław Bruś
License: UNKNOWN
Keywords: validation,customized,error,messages
Platform: UNKNOWN
Classifier: Development Status :: 5 - Production/Stable
Classifier: Intended Audience :: Developers
Classifier: License :: OSI Approved :: MIT License
Classifier: Operating System :: OS Independent
Classifier: Programming Language :: Python
Classifier: Programming Language :: Python :: 3.6
Classifier: Programming Language :: Python :: 3.7
Classifier: Programming Language :: Python :: 3.8
Classifier: Topic :: Utilities
Requires-Python: >=3.6
Requires-Dist: setuptools
Requires-Dist: Cerberus (==1.3.2)
